quickmpc/README.md
quickmpc/__init__.py
quickmpc/_version.py
quickmpc/exception.py
quickmpc/qmpc.py
quickmpc/qmpc_logging.py
quickmpc/version.py
quickmpc/pandas/__init__.py
quickmpc/pandas/parser.py
quickmpc/pandas/progress.py
quickmpc/pandas/readers.py
quickmpc/pandas/share_data_frame.py
quickmpc/proto/README.md
quickmpc/proto/__init__.py
quickmpc/proto/libc_to_manage_pb2.py
quickmpc/proto/libc_to_manage_pb2.pyi
quickmpc/proto/libc_to_manage_pb2_grpc.py
quickmpc/proto/libc_to_manage_pb2_grpc.pyi
quickmpc/proto/common_types/__init__.py
quickmpc/proto/common_types/common_types_pb2.py
quickmpc/proto/common_types/common_types_pb2.pyi
quickmpc/request/__init__.py
quickmpc/request/qmpc_request.py
quickmpc/request/qmpc_request_interface.py
quickmpc/request/response.py
quickmpc/share/__init__.py
quickmpc/share/random.py
quickmpc/share/restore.py
quickmpc/share/share.py
quickmpc/utils/__init__.py
quickmpc/utils/if_present.py
quickmpc/utils/make_pieces.py
quickmpc/utils/overload_tools.py
tests/__init__.py
tests/unit_tests/__init__.py
tests/unit_tests/conftest.py
tests/unit_tests/local_server.py
tests/unit_tests/test_qmpc.py
tests/unit_tests/pandas/__init__.py
tests/unit_tests/pandas/test_parser.py
tests/unit_tests/pandas/test_reader.py
tests/unit_tests/pandas/test_share_data_frame.py
tests/unit_tests/request/__init__.py
tests/unit_tests/request/test_qmpc_request.py
tests/unit_tests/share/__init__.py
tests/unit_tests/share/test_random.py
tests/unit_tests/share/test_restore.py
tests/unit_tests/share/test_share_recons.py
tests/unit_tests/share/test_share_sharize.py
tests/unit_tests/utils/__init__.py
tests/unit_tests/utils/test_make_pieces.py
tests/unit_tests/utils/test_over_load.py
quickmpc-1.1.1.dist-info/LICENSE
quickmpc-1.1.1.dist-info/METADATA
quickmpc-1.1.1.dist-info/WHEEL
quickmpc-1.1.1.dist-info/top_level.txt
quickmpc-1.1.1.dist-info/RECORD
