Metadata-Version: 2.1
Name: quickmpc
Version: 1.1.1
Author: Acompany
License: Apache 2.0 Licences
Requires-Python: >=3.7
License-File: LICENSE
Requires-Dist: numpy
Requires-Dist: grpcio-tools
Requires-Dist: grpcio-status
Requires-Dist: pynacl
Requires-Dist: tqdm
Requires-Dist: natsort
Requires-Dist: pandas
